src/chip.v
module mini_light_up_game (
    input clk,           // Horloge système
    input reset,         // Reset du jeu
    input btn,           // Bouton du joueur [cite: 4, 18]
    output [6:0] segments, // Sortie vers le bus segments commun 
    output [3:0] digit_sel // Sélection de l'afficheur (Anodes/Cathodes)
);
    // coucou
    // --- 1. Traitement du bouton (Anti-rebond / Impulsion unique) ---
    // [cite: 19, 20]
    reg btn_prev;
    wire btn_pulse;
    always @(posedge clk) btn_prev <= btn;
    assign btn_pulse = btn && !btn_prev;

    // --- 2. Registre Circulaire (Curseur) ---
    // [cite: 13, 14]
    reg [5:0] cursor;
    always @(posedge clk) begin
        if (reset) cursor <= 6'b000001;
        else cursor <= {cursor[4:0], cursor[5]}; // Décalage circulaire
    end

    // --- 3. Mémoire des 4 Afficheurs ---
    // Chaque afficheur a sa propre mémoire de 7 segments [cite: 21, 22]
    reg [6:0] mem [3:0]; 
    reg [1:0] active_digit; // Index de l'afficheur que le joueur tente de remplir

    always @(posedge clk) begin
        if (reset) begin
            active_digit <= 0;
            mem[0] <= 7'b0; mem[1] <= 7'b0; mem[2] <= 7'b0; mem[3] <= 7'b0;
        end else if (btn_pulse) begin
            // On "bloque" la position du curseur dans la mémoire de l'afficheur actif [cite: 8, 23]
            // Note: Le curseur ici active un segment spécifique pour former le '0'
            mem[active_digit] <= mem[active_digit] | {1'b0, cursor}; 
            
            // Si l'afficheur actuel est complet (ou après l'appui), on passe au suivant
            if (active_digit < 3) active_digit <= active_digit + 1;
        end
    end

    // --- 4. Multiplexage d'Affichage ---
    // Un compteur rapide pour basculer entre les afficheurs (Persistance rétinienne)
    reg [15:0] refresh_counter; 
    always @(posedge clk) refresh_counter <= refresh_counter + 1;

    wire [1:0] scan_idx = refresh_counter[15:14]; // Vitesse de balayage

    // Décodage pour activer un seul afficheur à la fois
    assign digit_sel = (scan_idx == 2'b00) ? 4'b1110 :
                       (scan_idx == 2'b01) ? 4'b1101 :
                       (scan_idx == 2'b10) ? 4'b1011 : 4'b0111;

    // Envoi de la mémoire correspondante sur le bus commun 
    assign segments = mem[scan_idx];

endmodule

src/testbench.v
`timescale 1ns / 1ps

module tb_mini_light_up_game;

    // Signaux d'entrée (reg dans le testbench)
    reg clk;
    reg reset;
    reg btn;

    // Signaux de sortie (wire dans le testbench)
    wire [6:0] segments;
    wire [3:0] digit_sel;

    // Instanciation de votre module
    mini_light_up_game uut (
        .clk(clk),
        .reset(reset),
        .btn(btn),
        .segments(segments),
        .digit_sel(digit_sel)
    );

    // Génération de l'horloge (période de 10ns = 100MHz)
    always #5 clk = ~clk;

    initial begin
        // --- Initialisation ---
        clk = 0;
        reset = 1;
        btn = 0;

        // Attente et relâchement du reset
        #20 reset = 0;
        $display("Sortie du reset...");

        // --- Test 1 : Observer le registre circulaire ---
        // On laisse le curseur tourner quelques cycles
        #100;

        // --- Test 2 : Premier appui bouton (Afficheur 1) ---
        // Le joueur tente de bloquer un segment
        $display("Appui bouton - Afficheur 1");
        btn = 1;
        #20; // Maintenir l'appui
        btn = 0;
        
        #200; // Laisser le temps au système de traiter

        // --- Test 3 : Deuxième appui bouton (Afficheur 2) ---
        $display("Appui bouton - Afficheur 2");
        btn = 1;
        #20;
        btn = 0;

        // --- Test 4 : Observer le multiplexage ---
        // On attend assez longtemps pour voir digit_sel changer (balayage)
        $display("Observation du balayage des afficheurs...");
        #1000;

        $display("Fin de la simulation");
        $finish;
    end

    // Visualisation des signaux dans la console (optionnel)
    initial begin
        $monitor("Temps=%0t | Digit_Sel=%b | Segments=%b | Cursor=%b", 
                 $time, digit_sel, segments, uut.cursor);
    end

endmodule

src/wave.vcd
$date
	Thu Apr  2 09:58:10 2026
$end
$version
	Icarus Verilog
$end
$timescale
	1ps
$end
$scope module tb_mini_light_up_game $end
$var wire 7 ! segments [6:0] $end
$var wire 4 " digit_sel [3:0] $end
$var reg 1 # btn $end
$var reg 1 $ clk $end
$var reg 1 % reset $end
$scope module uut $end
$var wire 1 # btn $end
$var wire 1 & btn_pulse $end
$var wire 1 $ clk $end
$var wire 1 % reset $end
$var wire 7 ' segments [6:0] $end
$var wire 2 ( scan_idx [1:0] $end
$var wire 4 ) digit_sel [3:0] $end
$var reg 2 * active_digit [1:0] $end
$var reg 1 + btn_prev $end
$var reg 6 , cursor [5:0] $end
$var reg 16 - refresh_counter [15:0] $end
$upscope $end
$upscope $end
$scope module tb_mini_light_up_game $end
$scope module uut $end
$upscope $end
$upscope $end
$enddefinitions $end
$comment Show the parameter values. $end
$dumpall
$end
#0
$dumpvars
bx -
bx ,
x+
bx *
bx )
bx (
bx '
0&
1%
0$
0#
bx "
bx !
$end
#5000
0+
b1 ,
b0 *
1$
#10000
0$
#15000
1$
#20000
0$
0%
#25000
b10 ,
1$
#30000
0$
#35000
b100 ,
1$
#40000
0$
#45000
b1000 ,
1$
#50000
0$
#55000
b10000 ,
1$
#60000
0$
#65000
b100000 ,
1$
#70000
0$
#75000
b1 ,
1$
#80000
0$
#85000
b10 ,
1$
#90000
0$
#95000
b100 ,
1$
#100000
0$
#105000
b1000 ,
1$
#110000
0$
#115000
b10000 ,
1$
#120000
1&
0$
1#
#125000
0&
1+
b100000 ,
b1 *
1$
#130000
0$
#135000
b1 ,
1$
#140000
0$
0#
#145000
0+
b10 ,
1$
#150000
0$
#155000
b100 ,
1$
#160000
0$
#165000
b1000 ,
1$
#170000
0$
#175000
b10000 ,
1$
#180000
0$
#185000
b100000 ,
1$
#190000
0$
#195000
b1 ,
1$
#200000
0$
#205000
b10 ,
1$
#210000
0$
#215000
b100 ,
1$
#220000
0$
#225000
b1000 ,
1$
#230000
0$
#235000
b10000 ,
1$
#240000
0$
#245000
b100000 ,
1$
#250000
0$
#255000
b1 ,
1$
#260000
0$
#265000
b10 ,
1$
#270000
0$
#275000
b100 ,
1$
#280000
0$
#285000
b1000 ,
1$
#290000
0$
#295000
b10000 ,
1$
#300000
0$
#305000
b100000 ,
1$
#310000
0$
#315000
b1 ,
1$
#320000
0$
#325000
b10 ,
1$
#330000
0$
#335000
b100 ,
1$
#340000
1&
0$
1#
#345000
0&
1+
b1000 ,
b10 *
1$
#350000
0$
#355000
b10000 ,
1$
#360000
0$
0#
#365000
0+
b100000 ,
1$
#370000
0$
#375000
b1 ,
1$
#380000
0$
#385000
b10 ,
1$
#390000
0$
#395000
b100 ,
1$
#400000
0$
#405000
b1000 ,
1$
#410000
0$
#415000
b10000 ,
1$
#420000
0$
#425000
b100000 ,
1$
#430000
0$
#435000
b1 ,
1$
#440000
0$
#445000
b10 ,
1$
#450000
0$
#455000
b100 ,
1$
#460000
0$
#465000
b1000 ,
1$
#470000
0$
#475000
b10000 ,
1$
#480000
0$
#485000
b100000 ,
1$
#490000
0$
#495000
b1 ,
1$
#500000
0$
#505000
b10 ,
1$
#510000
0$
#515000
b100 ,
1$
#520000
0$
#525000
b1000 ,
1$
#530000
0$
#535000
b10000 ,
1$
#540000
0$
#545000
b100000 ,
1$
#550000
0$
#555000
b1 ,
1$
#560000
0$
#565000
b10 ,
1$
#570000
0$
#575000
b100 ,
1$
#580000
0$
#585000
b1000 ,
1$
#590000
0$
#595000
b10000 ,
1$
#600000
0$
#605000
b100000 ,
1$
#610000
0$
#615000
b1 ,
1$
#620000
0$
#625000
b10 ,
1$
#630000
0$
#635000
b100 ,
1$
#640000
0$
#645000
b1000 ,
1$
#650000
0$
#655000
b10000 ,
1$
#660000
0$
#665000
b100000 ,
1$
#670000
0$
#675000
b1 ,
1$
#680000
0$
#685000
b10 ,
1$
#690000
0$
#695000
b100 ,
1$
#700000
0$
#705000
b1000 ,
1$
#710000
0$
#715000
b10000 ,
1$
#720000
0$
#725000
b100000 ,
1$
#730000
0$
#735000
b1 ,
1$
#740000
0$
#745000
b10 ,
1$
#750000
0$
#755000
b100 ,
1$
#760000
0$
#765000
b1000 ,
1$
#770000
0$
#775000
b10000 ,
1$
#780000
0$
#785000
b100000 ,
1$
#790000
0$
#795000
b1 ,
1$
#800000
0$
#805000
b10 ,
1$
#810000
0$
#815000
b100 ,
1$
#820000
0$
#825000
b1000 ,
1$
#830000
0$
#835000
b10000 ,
1$
#840000
0$
#845000
b100000 ,
1$
#850000
0$
#855000
b1 ,
1$
#860000
0$
#865000
b10 ,
1$
#870000
0$
#875000
b100 ,
1$
#880000
0$
#885000
b1000 ,
1$
#890000
0$
#895000
b10000 ,
1$
#900000
0$
#905000
b100000 ,
1$
#910000
0$
#915000
b1 ,
1$
#920000
0$
#925000
b10 ,
1$
#930000
0$
#935000
b100 ,
1$
#940000
0$
#945000
b1000 ,
1$
#950000
0$
#955000
b10000 ,
1$
#960000
0$
#965000
b100000 ,
1$
#970000
0$
#975000
b1 ,
1$
#980000
0$
#985000
b10 ,
1$
#990000
0$
#995000
b100 ,
1$
#1000000
0$
#1005000
b1000 ,
1$
#1010000
0$
#1015000
b10000 ,
1$
#1020000
0$
#1025000
b100000 ,
1$
#1030000
0$
#1035000
b1 ,
1$
#1040000
0$
#1045000
b10 ,
1$
#1050000
0$
#1055000
b100 ,
1$
#1060000
0$
#1065000
b1000 ,
1$
#1070000
0$
#1075000
b10000 ,
1$
#1080000
0$
#1085000
b100000 ,
1$
#1090000
0$
#1095000
b1 ,
1$
#1100000
0$
#1105000
b10 ,
1$
#1110000
0$
#1115000
b100 ,
1$
#1120000
0$
#1125000
b1000 ,
1$
#1130000
0$
#1135000
b10000 ,
1$
#1140000
0$
#1145000
b100000 ,
1$
#1150000
0$
#1155000
b1 ,
1$
#1160000
0$
#1165000
b10 ,
1$
#1170000
0$
#1175000
b100 ,
1$
#1180000
0$
#1185000
b1000 ,
1$
#1190000
0$
#1195000
b10000 ,
1$
#1200000
0$
#1205000
b100000 ,
1$
#1210000
0$
#1215000
b1 ,
1$
#1220000
0$
#1225000
b10 ,
1$
#1230000
0$
#1235000
b100 ,
1$
#1240000
0$
#1245000
b1000 ,
1$
#1250000
0$
#1255000
b10000 ,
1$
#1260000
0$
#1265000
b100000 ,
1$
#1270000
0$
#1275000
b1 ,
1$
#1280000
0$
#1285000
b10 ,
1$
#1290000
0$
#1295000
b100 ,
1$
#1300000
0$
#1305000
b1000 ,
1$
#1310000
0$
#1315000
b10000 ,
1$
#1320000
0$
#1325000
b100000 ,
1$
#1330000
0$
#1335000
b1 ,
1$
#1340000
0$
#1345000
b10 ,
1$
#1350000
0$
#1355000
b100 ,
1$
