src/chip.v

module mini_light_up_game (
    input  clk,         
    input  reset,       
    input  btn,         
    output [6:0] seg0,  
    output [6:0] seg1,  
    output [6:0] seg2,  
    output [6:0] seg3   
);

    
    reg btn_prev;
    wire btn_pulse;
    always @(posedge clk or posedge reset) begin
        if (reset) btn_prev <= 1'b0;
        else       btn_prev <= btn;
    end
    assign btn_pulse = btn & ~btn_prev;

    
    reg [5:0] cursor;
    always @(posedge clk or posedge reset) begin
        if (reset) cursor <= 6'b000001;
        else       cursor <= {cursor[4:0], cursor[5]};
    end

   
    reg [1:0] cnt;

   
    reg [5:0] mem0, mem1, mem2, mem3;

   
    reg [3:0] done_ff;

    wire sel0 = (cnt == 2'b00);
    wire sel1 = (cnt == 2'b01);
    wire sel2 = (cnt == 2'b10);
    wire sel3 = (cnt == 2'b11);

    wire wr0 = btn_pulse & sel0;
    wire wr1 = btn_pulse & sel1;
    wire wr2 = btn_pulse & sel2;
    wire wr3 = btn_pulse & sel3;

    wire [5:0] nxt0 = wr0 ? (mem0 | cursor) : mem0;
    wire [5:0] nxt1 = wr1 ? (mem1 | cursor) : mem1;
    wire [5:0] nxt2 = wr2 ? (mem2 | cursor) : mem2;
    wire [5:0] nxt3 = wr3 ? (mem3 | cursor) : mem3;

    
    wire [3:0] done_comb;
    assign done_comb[0] = &nxt0;
    assign done_comb[1] = &nxt1;
    assign done_comb[2] = &nxt2;
    assign done_comb[3] = &nxt3;


    wire cnt_advance = btn_pulse & done_ff[cnt] & ~sel3;

    always @(posedge clk or posedge reset) begin
        if (reset) begin
            cnt     <= 2'b00;
            mem0    <= 6'b0;  mem1 <= 6'b0;
            mem2    <= 6'b0;  mem3 <= 6'b0;
            done_ff <= 4'b0;
        end else begin
           
            mem0 <= nxt0;
            mem1 <= nxt1;
            mem2 <= nxt2;
            mem3 <= nxt3;
           
            done_ff <= done_comb;
           
            if (cnt_advance)
                cnt <= cnt + 1'b1;
        end
    end

    // 
    assign seg0 = {1'b0, mem0 | (cursor & {6{sel0}})};
    assign seg1 = {1'b0, mem1 | (cursor & {6{sel1}})};
    assign seg2 = {1'b0, mem2 | (cursor & {6{sel2}})};
    assign seg3 = {1'b0, mem3 | (cursor & {6{sel3}})};

endmodule

src/testbench.v
`timescale 1ns / 1ps

module tb_mini_light_up_game;

    // =========================
    // Signaux
    // =========================
    reg clk;
    reg reset;
    reg btn;

    wire [6:0] seg0, seg1, seg2, seg3;

    // =========================
    // DUT (Device Under Test)
    // =========================
    mini_light_up_game uut (
        .clk(clk),
        .reset(reset),
        .btn(btn),
        .seg0(seg0),
        .seg1(seg1),
        .seg2(seg2),
        .seg3(seg3)
    );

    // =========================
    // Horloge (40 MHz — CLOCK_PERIOD = 25 ns)
    // =========================
    always #12.5 clk = ~clk;

    // Tâche utilitaire : impulsion bouton d'1 cycle
    task press_btn;
        begin
            @(negedge clk);
            btn = 1;
            @(negedge clk);
            btn = 0;
        end
    endtask

    // =========================
    // Dump VCD (GTKWave)
    // =========================
    initial begin
        $dumpfile("wave.vcd");
        $dumpvars(0, tb_mini_light_up_game);
        $dumpvars(1, uut);
    end

    // =========================
    // Stimuli
    // =========================
    initial begin
        // Init
        clk   = 0;
        reset = 1;
        btn   = 0;

        // Reset (2 cycles)
        @(negedge clk); @(negedge clk);
        reset = 0;
        $display("t=%0t | Sortie du reset", $time);

        // Laisser le curseur tourner quelques cycles
        repeat(10) @(negedge clk);

        // --- Digit 0 : verrouiller les 6 segments (7 cycles/appui → couvre les 6 positions) ---
        $display("t=%0t | Remplissage digit 0", $time);
        repeat(6) begin
            press_btn;
            repeat(5) @(negedge clk); // 2+5=7 cycles/appui ; 7 mod 6=1 → toutes les positions
        end
        // Appui de validation : done_ff[0]=1 → cnt avance de 0 à 1
        press_btn;
        repeat(5) @(negedge clk);

        // --- Digit 1 ---
        $display("t=%0t | Remplissage digit 1", $time);
        repeat(6) begin
            press_btn;
            repeat(5) @(negedge clk);
        end
        // Appui de validation : cnt avance de 1 à 2
        press_btn;
        repeat(5) @(negedge clk);

        // --- Digit 2 ---
        $display("t=%0t | Remplissage digit 2", $time);
        repeat(6) begin
            press_btn;
            repeat(5) @(negedge clk);
        end
        // Appui de validation : cnt avance de 2 à 3
        press_btn;
        repeat(5) @(negedge clk);

        // --- Digit 3 ---
        $display("t=%0t | Remplissage digit 3", $time);
        repeat(6) begin
            press_btn;
            repeat(5) @(negedge clk);
        end

        repeat(20) @(negedge clk);
        $display("t=%0t | Fin simulation", $time);
        $finish;
    end

    // =========================
    // Monitoring console
    // =========================
    initial begin
        $monitor("t=%0t | seg0=%7b seg1=%7b seg2=%7b seg3=%7b",
                 $time, seg0, seg1, seg2, seg3);
    end

endmodule

src/wave.vcd
$date
	Tue May  5 10:59:15 2026
$end
$version
	Icarus Verilog
$end
$timescale
	1ps
$end
$scope module tb_mini_light_up_game $end
$var wire 7 ! seg3 [6:0] $end
$var wire 7 " seg2 [6:0] $end
$var wire 7 # seg1 [6:0] $end
$var wire 7 $ seg0 [6:0] $end
$var reg 1 % btn $end
$var reg 1 & clk $end
$var reg 1 ' reset $end
$scope module uut $end
$var wire 1 % btn $end
$var wire 1 ( btn_pulse $end
$var wire 1 & clk $end
$var wire 1 ) cnt_advance $end
$var wire 1 ' reset $end
$var wire 1 * wr0 $end
$var wire 1 + wr1 $end
$var wire 1 , wr2 $end
$var wire 1 - wr3 $end
$var wire 1 . sel3 $end
$var wire 1 / sel2 $end
$var wire 1 0 sel1 $end
$var wire 1 1 sel0 $end
$var wire 7 2 seg3 [6:0] $end
$var wire 7 3 seg2 [6:0] $end
$var wire 7 4 seg1 [6:0] $end
$var wire 7 5 seg0 [6:0] $end
$var wire 6 6 nxt3 [5:0] $end
$var wire 6 7 nxt2 [5:0] $end
$var wire 6 8 nxt1 [5:0] $end
$var wire 6 9 nxt0 [5:0] $end
$var wire 4 : done_comb [3:0] $end
$var reg 1 ; btn_prev $end
$var reg 2 < cnt [1:0] $end
$var reg 6 = cursor [5:0] $end
$var reg 4 > done_ff [3:0] $end
$var reg 6 ? mem0 [5:0] $end
$var reg 6 @ mem1 [5:0] $end
$var reg 6 A mem2 [5:0] $end
$var reg 6 B mem3 [5:0] $end
$upscope $end
$scope task press_btn $end
$upscope $end
$upscope $end
$scope module tb_mini_light_up_game $end
$scope module uut $end
$upscope $end
$upscope $end
$enddefinitions $end
$comment Show the parameter values. $end
$dumpall
$end
#0
$dumpvars
b0 B
b0 A
b0 @
b0 ?
b0 >
b1 =
b0 <
0;
b0 :
b0 9
b0 8
b0 7
b0 6
b1 5
b0 4
b0 3
b0 2
11
00
0/
0.
0-
0,
0+
0*
0)
0(
1'
0&
0%
b1 $
b0 #
b0 "
b0 !
$end
#12500
1&
#25000
0&
#37500
1&
#50000
0'
0&
#62500
b10 $
b10 5
b10 =
1&
#75000
0&
#87500
b100 $
b100 5
b100 =
1&
#100000
0&
#112500
b1000 $
b1000 5
b1000 =
1&
#125000
0&
#137500
b10000 $
b10000 5
b10000 =
1&
#150000
0&
#162500
b100000 $
b100000 5
b100000 =
1&
#175000
0&
#187500
b1 $
b1 5
b1 =
1&
#200000
0&
#212500
b10 $
b10 5
b10 =
1&
#225000
0&
#237500
b100 $
b100 5
b100 =
1&
#250000
0&
#262500
b1000 $
b1000 5
b1000 =
1&
#275000
0&
#287500
b10000 $
b10000 5
b10000 =
1&
#300000
0&
#312500
b100000 $
b100000 5
b100000 =
1&
#325000
b100000 9
1*
1(
1%
0&
#337500
0*
0(
b100001 $
b100001 5
b100000 9
1;
b1 =
b100000 ?
1&
#350000
0%
0&
#362500
b100010 $
b100010 5
b10 =
0;
1&
#375000
0&
#387500
b100100 $
b100100 5
b100 =
1&
#400000
0&
#412500
b101000 $
b101000 5
b1000 =
1&
#425000
0&
#437500
b110000 $
b110000 5
b10000 =
1&
#450000
0&
#462500
b100000 $
b100000 5
b100000 =
1&
#475000
0&
#487500
b100001 $
b100001 5
b1 =
1&
#500000
0&
#512500
b100010 $
b100010 5
b10 =
1&
#525000
b100010 9
1*
1(
1%
0&
#537500
0*
0(
b100110 $
b100110 5
b100010 9
1;
b100 =
b100010 ?
1&
#550000
0%
0&
#562500
b101010 $
b101010 5
b1000 =
0;
1&
#575000
0&
#587500
b110010 $
b110010 5
b10000 =
1&
#600000
0&
#612500
b100010 $
b100010 5
b100000 =
1&
#625000
0&
#637500
b100011 $
b100011 5
b1 =
1&
#650000
0&
#662500
b100010 $
b100010 5
b10 =
1&
#675000
0&
#687500
b100110 $
b100110 5
b100 =
1&
#700000
0&
#712500
b101010 $
b101010 5
b1000 =
1&
#725000
b101010 9
1*
1(
1%
0&
#737500
0*
0(
b111010 $
b111010 5
b101010 9
1;
b10000 =
b101010 ?
1&
#750000
0%
0&
#762500
b101010 $
b101010 5
b100000 =
0;
1&
#775000
0&
#787500
b101011 $
b101011 5
b1 =
1&
#800000
0&
#812500
b101010 $
b101010 5
b10 =
1&
#825000
0&
#837500
b101110 $
b101110 5
b100 =
1&
#850000
0&
#862500
b101010 $
b101010 5
b1000 =
1&
#875000
0&
#887500
b111010 $
b111010 5
b10000 =
1&
#900000
0&
#912500
b101010 $
b101010 5
b100000 =
1&
#925000
1*
1(
1%
0&
#937500
0*
0(
b101011 $
b101011 5
b101010 9
1;
b1 =
1&
#950000
0%
0&
#962500
b101010 $
b101010 5
b10 =
0;
1&
#975000
0&
#987500
b101110 $
b101110 5
b100 =
1&
#1000000
0&
#1012500
b101010 $
b101010 5
b1000 =
1&
#1025000
0&
#1037500
b111010 $
b111010 5
b10000 =
1&
#1050000
0&
#1062500
b101010 $
b101010 5
b100000 =
1&
#1075000
0&
#1087500
b101011 $
b101011 5
b1 =
1&
#1100000
0&
#1112500
b101010 $
b101010 5
b10 =
1&
#1125000
1*
1(
1%
0&
#1137500
0*
0(
b101110 $
b101110 5
b101010 9
1;
b100 =
1&
#1150000
0%
0&
#1162500
b101010 $
b101010 5
b1000 =
0;
1&
#1175000
0&
#1187500
b111010 $
b111010 5
b10000 =
1&
#1200000
0&
#1212500
b101010 $
b101010 5
b100000 =
1&
#1225000
0&
#1237500
b101011 $
b101011 5
b1 =
1&
#1250000
0&
#1262500
b101010 $
b101010 5
b10 =
1&
#1275000
0&
#1287500
b101110 $
b101110 5
b100 =
1&
#1300000
0&
#1312500
b101010 $
b101010 5
b1000 =
1&
#1325000
1*
1(
1%
0&
#1337500
0*
0(
b111010 $
b111010 5
b101010 9
1;
b10000 =
1&
#1350000
0%
0&
#1362500
b101010 $
b101010 5
b100000 =
0;
1&
#1375000
0&
#1387500
b101011 $
b101011 5
b1 =
1&
#1400000
0&
#1412500
b101010 $
b101010 5
b10 =
1&
#1425000
0&
#1437500
b101110 $
b101110 5
b100 =
1&
#1450000
0&
#1462500
b101010 $
b101010 5
b1000 =
1&
#1475000
0&
#1487500
b111010 $
b111010 5
b10000 =
1&
#1500000
0&
#1512500
b101010 $
b101010 5
b100000 =
1&
#1525000
1*
1(
1%
0&
#1537500
0*
0(
b101011 $
b101011 5
b101010 9
1;
b1 =
1&
#1550000
0%
0&
#1562500
b101010 $
b101010 5
b10 =
0;
1&
#1575000
0&
#1587500
b101110 $
b101110 5
b100 =
1&
#1600000
0&
#1612500
b101010 $
b101010 5
b1000 =
1&
#1625000
0&
#1637500
b111010 $
b111010 5
b10000 =
1&
#1650000
0&
#1662500
b101010 $
b101010 5
b100000 =
1&
#1675000
0&
#1687500
b101011 $
b101011 5
b1 =
1&
#1700000
0&
#1712500
b101010 $
b101010 5
b10 =
1&
#1725000
1*
1(
1%
0&
#1737500
0*
0(
b101110 $
b101110 5
b101010 9
1;
b100 =
1&
#1750000
0%
0&
#1762500
b101010 $
b101010 5
b1000 =
0;
1&
#1775000
0&
#1787500
b111010 $
b111010 5
b10000 =
1&
#1800000
0&
#1812500
b101010 $
b101010 5
b100000 =
1&
#1825000
0&
#1837500
b101011 $
b101011 5
b1 =
1&
#1850000
0&
#1862500
b101010 $
b101010 5
b10 =
1&
#1875000
0&
#1887500
b101110 $
b101110 5
b100 =
1&
#1900000
0&
#1912500
b101010 $
b101010 5
b1000 =
1&
#1925000
1*
1(
1%
0&
#1937500
0*
0(
b111010 $
b111010 5
b101010 9
1;
b10000 =
1&
#1950000
0%
0&
#1962500
b101010 $
b101010 5
b100000 =
0;
1&
#1975000
0&
#1987500
b101011 $
b101011 5
b1 =
1&
#2000000
0&
#2012500
b101010 $
b101010 5
b10 =
1&
#2025000
0&
#2037500
b101110 $
b101110 5
b100 =
1&
#2050000
0&
#2062500
b101010 $
b101010 5
b1000 =
1&
#2075000
0&
#2087500
b111010 $
b111010 5
b10000 =
1&
#2100000
0&
#2112500
b101010 $
b101010 5
b100000 =
1&
#2125000
1*
1(
1%
0&
#2137500
0*
0(
b101011 $
b101011 5
b101010 9
1;
b1 =
1&
#2150000
0%
0&
#2162500
b101010 $
b101010 5
b10 =
0;
1&
#2175000
0&
#2187500
b101110 $
b101110 5
b100 =
1&
#2200000
0&
#2212500
b101010 $
b101010 5
b1000 =
1&
#2225000
0&
#2237500
b111010 $
b111010 5
b10000 =
1&
#2250000
0&
#2262500
b101010 $
b101010 5
b100000 =
1&
#2275000
0&
#2287500
b101011 $
b101011 5
b1 =
1&
#2300000
0&
#2312500
b101010 $
b101010 5
b10 =
1&
#2325000
1*
1(
1%
0&
#2337500
0*
0(
b101110 $
b101110 5
b101010 9
1;
b100 =
1&
#2350000
0%
0&
#2362500
b101010 $
b101010 5
b1000 =
0;
1&
#2375000
0&
#2387500
b111010 $
b111010 5
b10000 =
1&
#2400000
0&
#2412500
b101010 $
b101010 5
b100000 =
1&
#2425000
0&
#2437500
b101011 $
b101011 5
b1 =
1&
#2450000
0&
#2462500
b101010 $
b101010 5
b10 =
1&
#2475000
0&
#2487500
b101110 $
b101110 5
b100 =
1&
#2500000
0&
#2512500
b101010 $
b101010 5
b1000 =
1&
#2525000
1*
1(
1%
0&
#2537500
0*
0(
b111010 $
b111010 5
b101010 9
1;
b10000 =
1&
#2550000
0%
0&
#2562500
b101010 $
b101010 5
b100000 =
0;
1&
#2575000
0&
#2587500
b101011 $
b101011 5
b1 =
1&
#2600000
0&
#2612500
b101010 $
b101010 5
b10 =
1&
#2625000
0&
#2637500
b101110 $
b101110 5
b100 =
1&
#2650000
0&
#2662500
b101010 $
b101010 5
b1000 =
1&
#2675000
0&
#2687500
b111010 $
b111010 5
b10000 =
1&
#2700000
0&
#2712500
b101010 $
b101010 5
b100000 =
1&
#2725000
1*
1(
1%
0&
#2737500
0*
0(
b101011 $
b101011 5
b101010 9
1;
b1 =
1&
#2750000
0%
0&
#2762500
b101010 $
b101010 5
b10 =
0;
1&
#2775000
0&
#2787500
b101110 $
b101110 5
b100 =
1&
#2800000
0&
#2812500
b101010 $
b101010 5
b1000 =
1&
#2825000
0&
#2837500
b111010 $
b111010 5
b10000 =
1&
#2850000
0&
#2862500
b101010 $
b101010 5
b100000 =
1&
#2875000
0&
#2887500
b101011 $
b101011 5
b1 =
1&
#2900000
0&
#2912500
b101010 $
b101010 5
b10 =
1&
#2925000
1*
1(
1%
0&
#2937500
0*
0(
b101110 $
b101110 5
b101010 9
1;
b100 =
1&
#2950000
0%
0&
#2962500
b101010 $
b101010 5
b1000 =
0;
1&
#2975000
0&
#2987500
b111010 $
b111010 5
b10000 =
1&
#3000000
0&
#3012500
b101010 $
b101010 5
b100000 =
1&
#3025000
0&
#3037500
b101011 $
b101011 5
b1 =
1&
#3050000
0&
#3062500
b101010 $
b101010 5
b10 =
1&
#3075000
0&
#3087500
b101110 $
b101110 5
b100 =
1&
#3100000
0&
#3112500
b101010 $
b101010 5
b1000 =
1&
#3125000
1*
1(
1%
0&
#3137500
0*
0(
b111010 $
b111010 5
b101010 9
1;
b10000 =
1&
#3150000
0%
0&
#3162500
b101010 $
b101010 5
b100000 =
0;
1&
#3175000
0&
#3187500
b101011 $
b101011 5
b1 =
1&
#3200000
0&
#3212500
b101010 $
b101010 5
b10 =
1&
#3225000
0&
#3237500
b101110 $
b101110 5
b100 =
1&
#3250000
0&
#3262500
b101010 $
b101010 5
b1000 =
1&
#3275000
0&
#3287500
b111010 $
b111010 5
b10000 =
1&
#3300000
0&
#3312500
b101010 $
b101010 5
b100000 =
1&
#3325000
1*
1(
1%
0&
#3337500
0*
0(
b101011 $
b101011 5
b101010 9
1;
b1 =
1&
#3350000
0%
0&
#3362500
b101010 $
b101010 5
b10 =
0;
1&
#3375000
0&
#3387500
b101110 $
b101110 5
b100 =
1&
#3400000
0&
#3412500
b101010 $
b101010 5
b1000 =
1&
#3425000
0&
#3437500
b111010 $
b111010 5
b10000 =
1&
#3450000
0&
#3462500
b101010 $
b101010 5
b100000 =
1&
#3475000
0&
#3487500
b101011 $
b101011 5
b1 =
1&
#3500000
0&
#3512500
b101010 $
b101010 5
b10 =
1&
#3525000
1*
1(
1%
0&
#3537500
0*
0(
b101110 $
b101110 5
b101010 9
1;
b100 =
1&
#3550000
0%
0&
#3562500
b101010 $
b101010 5
b1000 =
0;
1&
#3575000
0&
#3587500
b111010 $
b111010 5
b10000 =
1&
#3600000
0&
#3612500
b101010 $
b101010 5
b100000 =
1&
#3625000
0&
#3637500
b101011 $
b101011 5
b1 =
1&
#3650000
0&
#3662500
b101010 $
b101010 5
b10 =
1&
#3675000
0&
#3687500
b101110 $
b101110 5
b100 =
1&
#3700000
0&
#3712500
b101010 $
b101010 5
b1000 =
1&
#3725000
1*
1(
1%
0&
#3737500
0*
0(
b111010 $
b111010 5
b101010 9
1;
b10000 =
1&
#3750000
0%
0&
#3762500
b101010 $
b101010 5
b100000 =
0;
1&
#3775000
0&
#3787500
b101011 $
b101011 5
b1 =
1&
#3800000
0&
#3812500
b101010 $
b101010 5
b10 =
1&
#3825000
0&
#3837500
b101110 $
b101110 5
b100 =
1&
#3850000
0&
#3862500
b101010 $
b101010 5
b1000 =
1&
#3875000
0&
#3887500
b111010 $
b111010 5
b10000 =
1&
#3900000
0&
#3912500
b101010 $
b101010 5
b100000 =
1&
#3925000
1*
1(
1%
0&
#3937500
0*
0(
b101011 $
b101011 5
b101010 9
1;
b1 =
1&
#3950000
0%
0&
#3962500
b101010 $
b101010 5
b10 =
0;
1&
#3975000
0&
#3987500
b101110 $
b101110 5
b100 =
1&
#4000000
0&
#4012500
b101010 $
b101010 5
b1000 =
1&
#4025000
0&
#4037500
b111010 $
b111010 5
b10000 =
1&
#4050000
0&
#4062500
b101010 $
b101010 5
b100000 =
1&
#4075000
0&
#4087500
b101011 $
b101011 5
b1 =
1&
#4100000
0&
#4112500
b101010 $
b101010 5
b10 =
1&
#4125000
1*
1(
1%
0&
#4137500
0*
0(
b101110 $
b101110 5
b101010 9
1;
b100 =
1&
#4150000
0%
0&
#4162500
b101010 $
b101010 5
b1000 =
0;
1&
#4175000
0&
#4187500
b111010 $
b111010 5
b10000 =
1&
#4200000
0&
#4212500
b101010 $
b101010 5
b100000 =
1&
#4225000
0&
#4237500
b101011 $
b101011 5
b1 =
1&
#4250000
0&
#4262500
b101010 $
b101010 5
b10 =
1&
#4275000
0&
#4287500
b101110 $
b101110 5
b100 =
1&
#4300000
0&
#4312500
b101010 $
b101010 5
b1000 =
1&
#4325000
1*
1(
1%
0&
#4337500
0*
0(
b111010 $
b111010 5
b101010 9
1;
b10000 =
1&
#4350000
0%
0&
#4362500
b101010 $
b101010 5
b100000 =
0;
1&
#4375000
0&
#4387500
b101011 $
b101011 5
b1 =
1&
#4400000
0&
#4412500
b101010 $
b101010 5
b10 =
1&
#4425000
0&
#4437500
b101110 $
b101110 5
b100 =
1&
#4450000
0&
#4462500
b101010 $
b101010 5
b1000 =
1&
#4475000
0&
#4487500
b111010 $
b111010 5
b10000 =
1&
#4500000
0&
#4512500
b101010 $
b101010 5
b100000 =
1&
#4525000
1*
1(
1%
0&
#4537500
0*
0(
b101011 $
b101011 5
b101010 9
1;
b1 =
1&
#4550000
0%
0&
#4562500
b101010 $
b101010 5
b10 =
0;
1&
#4575000
0&
#4587500
b101110 $
b101110 5
b100 =
1&
#4600000
0&
#4612500
b101010 $
b101010 5
b1000 =
1&
#4625000
0&
#4637500
b111010 $
b111010 5
b10000 =
1&
#4650000
0&
#4662500
b101010 $
b101010 5
b100000 =
1&
#4675000
0&
#4687500
b101011 $
b101011 5
b1 =
1&
#4700000
0&
#4712500
b101010 $
b101010 5
b10 =
1&
#4725000
1*
1(
1%
0&
#4737500
0*
0(
b101110 $
b101110 5
b101010 9
1;
b100 =
1&
#4750000
0%
0&
#4762500
b101010 $
b101010 5
b1000 =
0;
1&
#4775000
0&
#4787500
b111010 $
b111010 5
b10000 =
1&
#4800000
0&
#4812500
b101010 $
b101010 5
b100000 =
1&
#4825000
0&
#4837500
b101011 $
b101011 5
b1 =
1&
#4850000
0&
#4862500
b101010 $
b101010 5
b10 =
1&
#4875000
0&
#4887500
b101110 $
b101110 5
b100 =
1&
#4900000
0&
#4912500
b101010 $
b101010 5
b1000 =
1&
#4925000
1*
1(
1%
0&
#4937500
0*
0(
b111010 $
b111010 5
b101010 9
1;
b10000 =
1&
#4950000
0%
0&
#4962500
b101010 $
b101010 5
b100000 =
0;
1&
#4975000
0&
#4987500
b101011 $
b101011 5
b1 =
1&
#5000000
0&
#5012500
b101010 $
b101010 5
b10 =
1&
#5025000
0&
#5037500
b101110 $
b101110 5
b100 =
1&
#5050000
0&
#5062500
b101010 $
b101010 5
b1000 =
1&
#5075000
0&
#5087500
b111010 $
b111010 5
b10000 =
1&
#5100000
0&
#5112500
b101010 $
b101010 5
b100000 =
1&
#5125000
0&
#5137500
b101011 $
b101011 5
b1 =
1&
#5150000
0&
#5162500
b101010 $
b101010 5
b10 =
1&
#5175000
0&
#5187500
b101110 $
b101110 5
b100 =
1&
#5200000
0&
#5212500
b101010 $
b101010 5
b1000 =
1&
#5225000
0&
#5237500
b111010 $
b111010 5
b10000 =
1&
#5250000
0&
#5262500
b101010 $
b101010 5
b100000 =
1&
#5275000
0&
#5287500
b101011 $
b101011 5
b1 =
1&
#5300000
0&
#5312500
b101010 $
b101010 5
b10 =
1&
#5325000
0&
#5337500
b101110 $
b101110 5
b100 =
1&
#5350000
0&
#5362500
b101010 $
b101010 5
b1000 =
1&
#5375000
0&
#5387500
b111010 $
b111010 5
b10000 =
1&
#5400000
0&
#5412500
b101010 $
b101010 5
b100000 =
1&
#5425000
0&
#5437500
b101011 $
b101011 5
b1 =
1&
#5450000
0&
#5462500
b101010 $
b101010 5
b10 =
1&
#5475000
0&
#5487500
b101110 $
b101110 5
b100 =
1&
#5500000
0&
#5512500
b101010 $
b101010 5
b1000 =
1&
#5525000
0&
#5537500
b111010 $
b111010 5
b10000 =
1&
#5550000
0&
#5562500
b101010 $
b101010 5
b100000 =
1&
#5575000
0&
#5587500
b101011 $
b101011 5
b1 =
1&
